setup.py
lg_distributions/Binomialdistribution.py
lg_distributions/Gaussiandistribution.py
lg_distributions/Generaldistribution.py
lg_distributions/__init__.py
lg_distributions.egg-info/PKG-INFO
lg_distributions.egg-info/SOURCES.txt
lg_distributions.egg-info/dependency_links.txt
lg_distributions.egg-info/not-zip-safe
lg_distributions.egg-info/top_level.txt