Metadata-Version: 1.0
Name: lg-distributions
Version: 0.1
Summary: Gaussian and Binomial distributions
Home-page: UNKNOWN
Author: lenz
Author-email: UNKNOWN
License: UNKNOWN
Platform: UNKNOWN
